tabura/__init__.py
tabura/_version.py
tabura/welcome.py
tabura-0.0.1.dist-info/licenses/LICENSE
tabura-0.0.1.dist-info/METADATA
tabura-0.0.1.dist-info/WHEEL
tabura-0.0.1.dist-info/top_level.txt
tabura-0.0.1.dist-info/RECORD
