Metadata-Version: 2.4
Name: tabura
Version: 0.0.1
Summary: Tools for data in Python
Author-email: Bernardo Dionisi <bernardo.dionisi@gmail.com>
License: Apache 2.0
Project-URL: Homepage, https://github.com/bernardodionisi/tabura
Project-URL: Source, https://github.com/bernardodionisi/tabura
Project-URL: Issues, https://github.com/bernardodionisi/tabura/issues
Project-URL: Documentation, https://bernardodionisi.github.io/tabura/latest/
Keywords: tools for data
Classifier: Intended Audience :: Science/Research
Classifier: Intended Audience :: Education
Classifier: Intended Audience :: Developers
Classifier: Topic :: Software Development :: Libraries :: Python Modules
Classifier: Programming Language :: Python :: 3.10
Classifier: Programming Language :: Python :: 3.11
Classifier: Programming Language :: Python :: 3.12
Classifier: Operating System :: OS Independent
Requires-Python: >=3.10
License-File: LICENSE
Requires-Dist: polars<2.0.0,>=1.32.0
Requires-Dist: typing_extensions>=4.0.0
Provides-Extra: dev
Requires-Dist: ruff==0.1.4; extra == "dev"
Requires-Dist: pytest; extra == "dev"
Requires-Dist: pytest-cov[toml]; extra == "dev"
Requires-Dist: pytest-xdist; extra == "dev"
Requires-Dist: pytest-benchmark>=4.0.0; extra == "dev"
Requires-Dist: requests; extra == "dev"
Requires-Dist: pdfminer.six; extra == "dev"
Dynamic: license-file
